README.md
setup.py
auto_chromedriver/__init__.py
auto_chromedriver.egg-info/PKG-INFO
auto_chromedriver.egg-info/SOURCES.txt
auto_chromedriver.egg-info/dependency_links.txt
auto_chromedriver.egg-info/requires.txt
auto_chromedriver.egg-info/top_level.txt