Metadata-Version: 2.1
Name: auto-chromedriver
Version: 0.0.1
Summary: 
Home-page: https://github.com/AzizKpln/auto_chromedriver
Author: Aziz Kaplan
Author-email: AzizKpln@protonmail.com
License: GPL-3.0
Platform: UNKNOWN
Classifier: License :: OSI Approved :: GNU General Public License v3 (GPLv3)
Classifier: Programming Language :: Python :: 3
Classifier: Programming Language :: Python :: 3.8
